{"nodes": [{"id": "c_users_keert_desktop_projects_easm_collector_py", "label": "collector.py", "file_type": "code", "source_file": "collector.py", "source_location": "L1"}, {"id": "c_users_keert_desktop_projects_easm_collector_resolve_to_ip", "label": "resolve_to_ip()", "file_type": "code", "source_file": "collector.py", "source_location": "L21", "_callable": true}, {"id": "c_users_keert_desktop_projects_easm_collector_resolve_reverse_dns", "label": "resolve_reverse_dns()", "file_type": "code", "source_file": "collector.py", "source_location": "L35", "_callable": true}, {"id": "c_users_keert_desktop_projects_easm_collector_get_target_ips", "label": "get_target_ips()", "file_type": "code", "source_file": "collector.py", "source_location": "L46", "_callable": true}, {"id": "c_users_keert_desktop_projects_easm_collector_main", "label": "main()", "file_type": "code", "source_file": "collector.py", "source_location": "L83", "_callable": true}, {"id": "c_users_keert_desktop_projects_easm_collector_rationale_22", "label": "Helper to resolve domain strings to IP address if needed.", "file_type": "rationale", "source_file": "collector.py", "source_location": "L22"}, {"id": "c_users_keert_desktop_projects_easm_collector_rationale_47", "label": "Yields unique individual tuples of (ip, domain/hostname) from the configured ass", "file_type": "rationale", "source_file": "collector.py", "source_location": "L47"}], "edges": [{"source": "c_users_keert_desktop_projects_easm_collector_py", "target": "ipaddress", "relation": "imports", "context": "import", "confidence": "EXTRACTED", "source_file": "collector.py", "source_location": "L1", "weight": 1.0}, {"source": "c_users_keert_desktop_projects_easm_collector_py", "target": "socket", "relation": "imports", "context": "import", "confidence": "EXTRACTED", "source_file": "collector.py", "source_location": "L2", "weight": 1.0}, {"source": "c_users_keert_desktop_projects_easm_collector_py", "target": "os", "relation": "imports", "context": "import", "confidence": "EXTRACTED", "source_file": "collector.py", "source_location": "L3", "weight": 1.0}, {"source": "c_users_keert_desktop_projects_easm_collector_py", "target": "dotenv", "relation": "imports_from", "context": "import", "confidence": "EXTRACTED", "source_file": "collector.py", "source_location": "L4", "weight": 1.0}, {"source": "c_users_keert_desktop_projects_easm_collector_py", "target": "core_splunk_client", "relation": "imports_from", "context": "import", "confidence": "EXTRACTED", "source_file": "collector.py", "source_location": "L7", "weight": 1.0}, {"source": "c_users_keert_desktop_projects_easm_collector_py", "target": "core_logger", "relation": "imports_from", "context": "import", "confidence": "EXTRACTED", "source_file": "collector.py", "source_location": "L8", "weight": 1.0}, {"source": "c_users_keert_desktop_projects_easm_collector_py", "target": "core_shodan_client", "relation": "imports_from", "context": "import", "confidence": "EXTRACTED", "source_file": "collector.py", "source_location": "L9", "weight": 1.0}, {"source": "c_users_keert_desktop_projects_easm_collector_py", "target": "core_censys_client", "relation": "imports_from", "context": "import", "confidence": "EXTRACTED", "source_file": "collector.py", "source_location": "L10", "weight": 1.0}, {"source": "c_users_keert_desktop_projects_easm_collector_py", "target": "core_normalizer", "relation": "imports_from", "context": "import", "confidence": "EXTRACTED", "source_file": "collector.py", "source_location": "L11", "weight": 1.0}, {"source": "c_users_keert_desktop_projects_easm_collector_py", "target": "core_risk_engine", "relation": "imports_from", "context": "import", "confidence": "EXTRACTED", "source_file": "collector.py", "source_location": "L12", "weight": 1.0}, {"source": "c_users_keert_desktop_projects_easm_collector_py", "target": "core_baseline", "relation": "imports_from", "context": "import", "confidence": "EXTRACTED", "source_file": "collector.py", "source_location": "L13", "weight": 1.0}, {"source": "c_users_keert_desktop_projects_easm_collector_py", "target": "core_config_loader", "relation": "imports_from", "context": "import", "confidence": "EXTRACTED", "source_file": "collector.py", "source_location": "L14", "weight": 1.0}, {"source": "c_users_keert_desktop_projects_easm_collector_py", "target": "core_crt_client", "relation": "imports_from", "context": "import", "confidence": "EXTRACTED", "source_file": "collector.py", "source_location": "L15", "weight": 1.0}, {"source": "c_users_keert_desktop_projects_easm_collector_py", "target": "core_active_scanner", "relation": "imports_from", "context": "import", "confidence": "EXTRACTED", "source_file": "collector.py", "source_location": "L16", "weight": 1.0}, {"source": "c_users_keert_desktop_projects_easm_collector_py", "target": "core_models", "relation": "imports_from", "context": "import", "confidence": "EXTRACTED", "source_file": "collector.py", "source_location": "L17", "weight": 1.0}, {"source": "c_users_keert_desktop_projects_easm_collector_py", "target": "c_users_keert_desktop_projects_easm_collector_resolve_to_ip", "relation": "contains", "confidence": "EXTRACTED", "source_file": "collector.py", "source_location": "L21", "weight": 1.0}, {"source": "c_users_keert_desktop_projects_easm_collector_py", "target": "c_users_keert_desktop_projects_easm_collector_resolve_reverse_dns", "relation": "contains", "confidence": "EXTRACTED", "source_file": "collector.py", "source_location": "L35", "weight": 1.0}, {"source": "c_users_keert_desktop_projects_easm_collector_py", "target": "c_users_keert_desktop_projects_easm_collector_get_target_ips", "relation": "contains", "confidence": "EXTRACTED", "source_file": "collector.py", "source_location": "L46", "weight": 1.0}, {"source": "c_users_keert_desktop_projects_easm_collector_py", "target": "c_users_keert_desktop_projects_easm_collector_main", "relation": "contains", "confidence": "EXTRACTED", "source_file": "collector.py", "source_location": "L83", "weight": 1.0}, {"source": "c_users_keert_desktop_projects_easm_collector_get_target_ips", "target": "c_users_keert_desktop_projects_easm_collector_resolve_to_ip", "relation": "calls", "context": "call", "confidence": "EXTRACTED", "source_file": "collector.py", "source_location": "L64", "weight": 1.0}, {"source": "c_users_keert_desktop_projects_easm_collector_main", "target": "c_users_keert_desktop_projects_easm_collector_get_target_ips", "relation": "calls", "context": "call", "confidence": "EXTRACTED", "source_file": "collector.py", "source_location": "L105", "weight": 1.0}, {"source": "c_users_keert_desktop_projects_easm_collector_main", "target": "c_users_keert_desktop_projects_easm_collector_resolve_reverse_dns", "relation": "calls", "context": "call", "confidence": "EXTRACTED", "source_file": "collector.py", "source_location": "L152", "weight": 1.0}, {"source": "c_users_keert_desktop_projects_easm_collector_rationale_22", "target": "c_users_keert_desktop_projects_easm_collector_resolve_to_ip", "relation": "rationale_for", "confidence": "EXTRACTED", "source_file": "collector.py", "source_location": "L22", "weight": 1.0}, {"source": "c_users_keert_desktop_projects_easm_collector_rationale_47", "target": "c_users_keert_desktop_projects_easm_collector_get_target_ips", "relation": "rationale_for", "confidence": "EXTRACTED", "source_file": "collector.py", "source_location": "L47", "weight": 1.0}], "raw_calls": [{"caller_nid": "c_users_keert_desktop_projects_easm_collector_resolve_to_ip", "callee": "ip_address", "is_member_call": true, "source_file": "collector.py", "source_location": "L24", "receiver": "ipaddress"}, {"caller_nid": "c_users_keert_desktop_projects_easm_collector_resolve_to_ip", "callee": "gethostbyname", "is_member_call": true, "source_file": "collector.py", "source_location": "L28", "receiver": "socket"}, {"caller_nid": "c_users_keert_desktop_projects_easm_collector_resolve_to_ip", "callee": "info", "is_member_call": true, "source_file": "collector.py", "source_location": "L29", "receiver": "logger"}, {"caller_nid": "c_users_keert_desktop_projects_easm_collector_resolve_to_ip", "callee": "error", "is_member_call": true, "source_file": "collector.py", "source_location": "L32", "receiver": "logger"}, {"caller_nid": "c_users_keert_desktop_projects_easm_collector_resolve_reverse_dns", "callee": "getdefaulttimeout", "is_member_call": true, "source_file": "collector.py", "source_location": "L36", "receiver": "socket"}, {"caller_nid": "c_users_keert_desktop_projects_easm_collector_resolve_reverse_dns", "callee": "setdefaulttimeout", "is_member_call": true, "source_file": "collector.py", "source_location": "L38", "receiver": "socket"}, {"caller_nid": "c_users_keert_desktop_projects_easm_collector_resolve_reverse_dns", "callee": "gethostbyaddr", "is_member_call": true, "source_file": "collector.py", "source_location": "L39", "receiver": "socket"}, {"caller_nid": "c_users_keert_desktop_projects_easm_collector_resolve_reverse_dns", "callee": "setdefaulttimeout", "is_member_call": true, "source_file": "collector.py", "source_location": "L44", "receiver": "socket"}, {"caller_nid": "c_users_keert_desktop_projects_easm_collector_get_target_ips", "callee": "load", "is_member_call": true, "source_file": "collector.py", "source_location": "L48", "receiver": null}, {"caller_nid": "c_users_keert_desktop_projects_easm_collector_get_target_ips", "callee": "ConfigLoader", "is_member_call": false, "source_file": "collector.py", "source_location": "L48", "receiver": null}, {"caller_nid": "c_users_keert_desktop_projects_easm_collector_get_target_ips", "callee": "CrtClient", "is_member_call": false, "source_file": "collector.py", "source_location": "L49", "receiver": null}, {"caller_nid": "c_users_keert_desktop_projects_easm_collector_get_target_ips", "callee": "get", "is_member_call": true, "source_file": "collector.py", "source_location": "L52", "receiver": "config"}, {"caller_nid": "c_users_keert_desktop_projects_easm_collector_get_target_ips", "callee": "get", "is_member_call": true, "source_file": "collector.py", "source_location": "L53", "receiver": "asset"}, {"caller_nid": "c_users_keert_desktop_projects_easm_collector_get_target_ips", "callee": "get", "is_member_call": true, "source_file": "collector.py", "source_location": "L54", "receiver": "asset"}, {"caller_nid": "c_users_keert_desktop_projects_easm_collector_get_target_ips", "callee": "ip_network", "is_member_call": true, "source_file": "collector.py", "source_location": "L57", "receiver": "ipaddress"}, {"caller_nid": "c_users_keert_desktop_projects_easm_collector_get_target_ips", "callee": "add", "is_member_call": true, "source_file": "collector.py", "source_location": "L60", "receiver": "scanned_ips"}, {"caller_nid": "c_users_keert_desktop_projects_easm_collector_get_target_ips", "callee": "add", "is_member_call": true, "source_file": "collector.py", "source_location": "L66", "receiver": "scanned_ips"}, {"caller_nid": "c_users_keert_desktop_projects_easm_collector_get_target_ips", "callee": "get_subdomains", "is_member_call": true, "source_file": "collector.py", "source_location": "L70", "receiver": "crt"}, {"caller_nid": "c_users_keert_desktop_projects_easm_collector_get_target_ips", "callee": "add", "is_member_call": true, "source_file": "collector.py", "source_location": "L74", "receiver": "scanned_ips"}, {"caller_nid": "c_users_keert_desktop_projects_easm_collector_get_target_ips", "callee": "add", "is_member_call": true, "source_file": "collector.py", "source_location": "L79", "receiver": "scanned_ips"}, {"caller_nid": "c_users_keert_desktop_projects_easm_collector_get_target_ips", "callee": "get", "is_member_call": true, "source_file": "collector.py", "source_location": "L80", "receiver": "asset"}, {"caller_nid": "c_users_keert_desktop_projects_easm_collector_main", "callee": "info", "is_member_call": true, "source_file": "collector.py", "source_location": "L84", "receiver": "logger"}, {"caller_nid": "c_users_keert_desktop_projects_easm_collector_main", "callee": "load", "is_member_call": true, "source_file": "collector.py", "source_location": "L85", "receiver": null}, {"caller_nid": "c_users_keert_desktop_projects_easm_collector_main", "callee": "ConfigLoader", "is_member_call": false, "source_file": "collector.py", "source_location": "L85", "receiver": null}, {"caller_nid": "c_users_keert_desktop_projects_easm_collector_main", "callee": "SplunkClient", "is_member_call": false, "source_file": "collector.py", "source_location": "L88", "receiver": null}, {"caller_nid": "c_users_keert_desktop_projects_easm_collector_main", "callee": "error", "is_member_call": true, "source_file": "collector.py", "source_location": "L90", "receiver": "logger"}, {"caller_nid": "c_users_keert_desktop_projects_easm_collector_main", "callee": "BaselineEngine", "is_member_call": false, "source_file": "collector.py", "source_location": "L93", "receiver": null}, {"caller_nid": "c_users_keert_desktop_projects_easm_collector_main", "callee": "InternetDBClient", "is_member_call": false, "source_file": "collector.py", "source_location": "L94", "receiver": null}, {"caller_nid": "c_users_keert_desktop_projects_easm_collector_main", "callee": "CensysClient", "is_member_call": false, "source_file": "collector.py", "source_location": "L95", "receiver": null}, {"caller_nid": "c_users_keert_desktop_projects_easm_collector_main", "callee": "ActiveScanner", "is_member_call": false, "source_file": "collector.py", "source_location": "L96", "receiver": null}, {"caller_nid": "c_users_keert_desktop_projects_easm_collector_main", "callee": "add", "is_member_call": true, "source_file": "collector.py", "source_location": "L106", "receiver": "scanned_ips_this_run"}, {"caller_nid": "c_users_keert_desktop_projects_easm_collector_main", "callee": "info", "is_member_call": true, "source_file": "collector.py", "source_location": "L107", "receiver": "logger"}, {"caller_nid": "c_users_keert_desktop_projects_easm_collector_main", "callee": "get_ip_info", "is_member_call": true, "source_file": "collector.py", "source_location": "L110", "receiver": "shodan"}, {"caller_nid": "c_users_keert_desktop_projects_easm_collector_main", "callee": "normalize_internetdb_response", "is_member_call": false, "source_file": "collector.py", "source_location": "L111", "receiver": null}, {"caller_nid": "c_users_keert_desktop_projects_easm_collector_main", "callee": "get_exposures", "is_member_call": true, "source_file": "collector.py", "source_location": "L114", "receiver": "censys"}, {"caller_nid": "c_users_keert_desktop_projects_easm_collector_main", "callee": "append", "is_member_call": true, "source_file": "collector.py", "source_location": "L120", "receiver": "events"}, {"caller_nid": "c_users_keert_desktop_projects_easm_collector_main", "callee": "add", "is_member_call": true, "source_file": "collector.py", "source_location": "L121", "receiver": "seen_ports"}, {"caller_nid": "c_users_keert_desktop_projects_easm_collector_main", "callee": "is_rustscan_available", "is_member_call": true, "source_file": "collector.py", "source_location": "L126", "receiver": "active"}, {"caller_nid": "c_users_keert_desktop_projects_easm_collector_main", "callee": "run_rustscan", "is_member_call": true, "source_file": "collector.py", "source_location": "L127", "receiver": "active"}, {"caller_nid": "c_users_keert_desktop_projects_easm_collector_main", "callee": "info", "is_member_call": true, "source_file": "collector.py", "source_location": "L129", "receiver": "logger"}, {"caller_nid": "c_users_keert_desktop_projects_easm_collector_main", "callee": "scan_ports_parallel", "is_member_call": true, "source_file": "collector.py", "source_location": "L131", "receiver": "active"}, {"caller_nid": "c_users_keert_desktop_projects_easm_collector_main", "callee": "append", "is_member_call": true, "source_file": "collector.py", "source_location": "L134", "receiver": "events"}, {"caller_nid": "c_users_keert_desktop_projects_easm_collector_main", "callee": "ExposureEvent", "is_member_call": false, "source_file": "collector.py", "source_location": "L135", "receiver": null}, {"caller_nid": "c_users_keert_desktop_projects_easm_collector_main", "callee": "is_port_open", "is_member_call": true, "source_file": "collector.py", "source_location": "L156", "receiver": "active"}, {"caller_nid": "c_users_keert_desktop_projects_easm_collector_main", "callee": "info", "is_member_call": true, "source_file": "collector.py", "source_location": "L157", "receiver": "logger"}, {"caller_nid": "c_users_keert_desktop_projects_easm_collector_main", "callee": "add", "is_member_call": true, "source_file": "collector.py", "source_location": "L162", "receiver": "active_exposures_this_run"}, {"caller_nid": "c_users_keert_desktop_projects_easm_collector_main", "callee": "get_status", "is_member_call": true, "source_file": "collector.py", "source_location": "L165", "receiver": "baseline"}, {"caller_nid": "c_users_keert_desktop_projects_easm_collector_main", "callee": "update_status", "is_member_call": true, "source_file": "collector.py", "source_location": "L169", "receiver": "baseline"}, {"caller_nid": "c_users_keert_desktop_projects_easm_collector_main", "callee": "to_dict", "is_member_call": true, "source_file": "collector.py", "source_location": "L171", "receiver": "event"}, {"caller_nid": "c_users_keert_desktop_projects_easm_collector_main", "callee": "get", "is_member_call": true, "source_file": "collector.py", "source_location": "L172", "receiver": "config"}, {"caller_nid": "c_users_keert_desktop_projects_easm_collector_main", "callee": "calculate_risk", "is_member_call": false, "source_file": "collector.py", "source_location": "L173", "receiver": null}, {"caller_nid": "c_users_keert_desktop_projects_easm_collector_main", "callee": "audit_sensitive_files", "is_member_call": true, "source_file": "collector.py", "source_location": "L178", "receiver": "active"}, {"caller_nid": "c_users_keert_desktop_projects_easm_collector_main", "callee": "warn", "is_member_call": true, "source_file": "collector.py", "source_location": "L182", "receiver": "logger"}, {"caller_nid": "c_users_keert_desktop_projects_easm_collector_main", "callee": "info", "is_member_call": true, "source_file": "collector.py", "source_location": "L185", "receiver": "logger"}, {"caller_nid": "c_users_keert_desktop_projects_easm_collector_main", "callee": "send_event", "is_member_call": true, "source_file": "collector.py", "source_location": "L187", "receiver": "splunk"}, {"caller_nid": "c_users_keert_desktop_projects_easm_collector_main", "callee": "get", "is_member_call": true, "source_file": "collector.py", "source_location": "L188", "receiver": "result"}, {"caller_nid": "c_users_keert_desktop_projects_easm_collector_main", "callee": "error", "is_member_call": true, "source_file": "collector.py", "source_location": "L189", "receiver": "logger"}, {"caller_nid": "c_users_keert_desktop_projects_easm_collector_main", "callee": "get", "is_member_call": true, "source_file": "collector.py", "source_location": "L189", "receiver": "result"}, {"caller_nid": "c_users_keert_desktop_projects_easm_collector_main", "callee": "get_currently_open", "is_member_call": true, "source_file": "collector.py", "source_location": "L192", "receiver": "baseline"}, {"caller_nid": "c_users_keert_desktop_projects_easm_collector_main", "callee": "split", "is_member_call": true, "source_file": "collector.py", "source_location": "L194", "receiver": "exp_id"}, {"caller_nid": "c_users_keert_desktop_projects_easm_collector_main", "callee": "update_status", "is_member_call": true, "source_file": "collector.py", "source_location": "L199", "receiver": "baseline"}, {"caller_nid": "c_users_keert_desktop_projects_easm_collector_main", "callee": "ExposureEvent", "is_member_call": false, "source_file": "collector.py", "source_location": "L201", "receiver": null}, {"caller_nid": "c_users_keert_desktop_projects_easm_collector_main", "callee": "to_dict", "is_member_call": true, "source_file": "collector.py", "source_location": "L211", "receiver": "resolved_event"}, {"caller_nid": "c_users_keert_desktop_projects_easm_collector_main", "callee": "warn", "is_member_call": true, "source_file": "collector.py", "source_location": "L214", "receiver": "logger"}, {"caller_nid": "c_users_keert_desktop_projects_easm_collector_main", "callee": "send_event", "is_member_call": true, "source_file": "collector.py", "source_location": "L216", "receiver": "splunk"}, {"caller_nid": "c_users_keert_desktop_projects_easm_collector_main", "callee": "get", "is_member_call": true, "source_file": "collector.py", "source_location": "L217", "receiver": "result"}, {"caller_nid": "c_users_keert_desktop_projects_easm_collector_main", "callee": "error", "is_member_call": true, "source_file": "collector.py", "source_location": "L218", "receiver": "logger"}, {"caller_nid": "c_users_keert_desktop_projects_easm_collector_main", "callee": "get", "is_member_call": true, "source_file": "collector.py", "source_location": "L218", "receiver": "result"}, {"caller_nid": "c_users_keert_desktop_projects_easm_collector_main", "callee": "info", "is_member_call": true, "source_file": "collector.py", "source_location": "L220", "receiver": "logger"}, {"caller_nid": "c_users_keert_desktop_projects_easm_collector_main", "callee": "info", "is_member_call": true, "source_file": "collector.py", "source_location": "L221", "receiver": "logger"}, {"caller_nid": "c_users_keert_desktop_projects_easm_collector_main", "callee": "info", "is_member_call": true, "source_file": "collector.py", "source_location": "L222", "receiver": "logger"}]}