{"C:\\Users\\keert\\Desktop\\Projects\\EASM\\README.md":{"size":1624,"mtime_ns":1784028892723739600,"word_count":187,"hashes":{"readme.md":"011c4af5e276664b0efceb6209250a19f559c531d0669e022bd2210c9dac7241"}},"C:\\Users\\keert\\Desktop\\Projects\\EASM\\api\\index.py":{"size":28997,"mtime_ns":1784561219782525200,"word_count":2417,"hashes":{"api/index.py":"805158b3ffd88a760ab70916b518f51f7ac5795f120ae191e29f71676697d753"}},"C:\\Users\\keert\\Desktop\\Projects\\EASM\\app.js":{"size":38310,"mtime_ns":1784561292813456900,"word_count":3088},"C:\\Users\\keert\\Desktop\\Projects\\EASM\\collector.py":{"size":8673,"mtime_ns":1784548513343313400,"word_count":727,"hashes":{"collector.py":"13701c68a65749b621c85e79eae3955e3719c74e2a4ff40e3ad5df8587ec9bc7"}},"C:\\Users\\keert\\Desktop\\Projects\\EASM\\config\\assets.yaml":{"size":90,"mtime_ns":1784532733051341600,"word_count":11,"hashes":{"config/assets.yaml":"d8a9b862b32cda117db51e943114fbfc6e172e0ec771925283eb47802fad7e7e"}},"C:\\Users\\keert\\Desktop\\Projects\\EASM\\configure.py":{"size":8925,"mtime_ns":1784528744782890300,"word_count":887,"hashes":{"configure.py":"36fe453059b68ab7ae6e3471321c695399038d148605d428dc159cc771dc931e"}},"C:\\Users\\keert\\Desktop\\Projects\\EASM\\context\\easm_dashboard_studio.json":{"size":10143,"mtime_ns":1784555187673093100,"word_count":607,"hashes":{"context/easm_dashboard_studio.json":"b413a70118fc444fd50e4f38b80a34ad2db5237ec26f553ba36c15381a8d2dfb"}},"C:\\Users\\keert\\Desktop\\Projects\\EASM\\context\\project_context.md":{"size":805,"mtime_ns":1784109384994388600,"word_count":112,"hashes":{"context/project_context.md":"d65b942e80b70f178293e27e7bb7f7ed586a27389996be418151195945a53135"}},"C:\\Users\\keert\\Desktop\\Projects\\EASM\\core\\active_scanner.py":{"size":5318,"mtime_ns":1784530561645740900,"word_count":531,"hashes":{"core/active_scanner.py":"08568dab4815a1e66dc86fa68da3d1abe81e86d2465d04712df011d57b3a755c"}},"C:\\Users\\keert\\Desktop\\Projects\\EASM\\core\\auth.py":{"size":15342,"mtime_ns":1784561210179982600,"word_count":1324,"hashes":{"core/auth.py":"4648301347ff53d5fa6baa9d6c0cad9d623b9ce14a85157ecfb6869255dbcb78"}},"C:\\Users\\keert\\Desktop\\Projects\\EASM\\core\\baseline.py":{"size":2512,"mtime_ns":1784538861949562100,"word_count":224,"hashes":{"core/baseline.py":"1df69b25e77fb658e7745fc044910bd6417a5d8bff9e2f831ae7561aabc60b4f"}},"C:\\Users\\keert\\Desktop\\Projects\\EASM\\core\\censys_client.py":{"size":3908,"mtime_ns":1784182145357394900,"word_count":334,"hashes":{"core/censys_client.py":"2667da25d823931209746d925263af4e2e9e2744639a3982102965f41b8a2b30"}},"C:\\Users\\keert\\Desktop\\Projects\\EASM\\core\\config_loader.py":{"size":1715,"mtime_ns":1784547269194635500,"word_count":132,"hashes":{"core/config_loader.py":"dd0d4cd6a364d5da6eae8c8adf0d3e3a04468061a31bffda0db1f463c8717ea3"}},"C:\\Users\\keert\\Desktop\\Projects\\EASM\\core\\crt_client.py":{"size":3099,"mtime_ns":1784113731394649400,"word_count":263,"hashes":{"core/crt_client.py":"8e1929b29cbe99ea05d49e057e59b6346d88427e62b7e015eee3341784d2713c"}},"C:\\Users\\keert\\Desktop\\Projects\\EASM\\core\\logger.py":{"size":466,"mtime_ns":1784108747838189500,"word_count":38,"hashes":{"core/logger.py":"894215f102fdeb47b086acc445d177f54cd983956fe139ce3f6f1bcc3d559719"}},"C:\\Users\\keert\\Desktop\\Projects\\EASM\\core\\models.py":{"size":468,"mtime_ns":1784120305255468300,"word_count":58,"hashes":{"core/models.py":"bd471a8b8b9c0c7718f4a79776e247107aa48c0ac06f34a16f3884b1015863a4"}},"C:\\Users\\keert\\Desktop\\Projects\\EASM\\core\\normalizer.py":{"size":736,"mtime_ns":1784109405645612900,"word_count":71,"hashes":{"core/normalizer.py":"f4c7161bf3aae05f27be7bd28a85bdd98d41bae15cd924e2c4edb35271739bf6"}},"C:\\Users\\keert\\Desktop\\Projects\\EASM\\core\\risk_engine.py":{"size":699,"mtime_ns":1784528707813530900,"word_count":95,"hashes":{"core/risk_engine.py":"3b07a5565dfc75bb551549cb0c27700e7efd8b2ddcecdc674762331b6f522578"}},"C:\\Users\\keert\\Desktop\\Projects\\EASM\\core\\shodan_client.py":{"size":1003,"mtime_ns":1784109213650336500,"word_count":101,"hashes":{"core/shodan_client.py":"b512c6cec6af4fb79d9a6a32d1e1534ca5c243d9f1f26d28486c19a4325d8cd5"}},"C:\\Users\\keert\\Desktop\\Projects\\EASM\\core\\splunk_client.py":{"size":2629,"mtime_ns":1784530119862997100,"word_count":213,"hashes":{"core/splunk_client.py":"dddc9f7567f17584db92967e23e2b3ff3d39ac966d7b71a8f3ba3892cf046d7b"}},"C:\\Users\\keert\\Desktop\\Projects\\EASM\\core\\splunk_sso.py":{"size":2225,"mtime_ns":1784549808001994400,"word_count":179,"hashes":{"core/splunk_sso.py":"b83775a129a1cba8e831fbd13ddfdb7f543801795734801b48ac781a209280f4"}},"C:\\Users\\keert\\Desktop\\Projects\\EASM\\data\\baseline.json":{"size":111,"mtime_ns":1784531408956961900,"word_count":8,"hashes":{"data/baseline.json":"3690a2740798d03ff7f1fd6b559090429f7099516ed2f3ea68a12c15e6d54cea"}},"C:\\Users\\keert\\Desktop\\Projects\\EASM\\data\\users.json":{"size":702,"mtime_ns":1784561351251541200,"word_count":36,"hashes":{"data/users.json":"39ed8bea913a330c2850d54bedfbeda817fb0c92dd2cc649479032ab750c923c"}},"C:\\Users\\keert\\Desktop\\Projects\\EASM\\easm_dashboard_studio.json":{"size":10143,"mtime_ns":1784555184830638600,"word_count":607,"hashes":{"easm_dashboard_studio.json":"bc9c022d8856e5a48e17fc5c57cd3185322be0d8b4fced57a0abc817b78fe85b"}},"C:\\Users\\keert\\Desktop\\Projects\\EASM\\favicon.svg":{"size":479,"mtime_ns":1784546705876700800,"word_count":43,"hashes":{"favicon.svg":"721c0621a54ffb9b34cae9351ef866a0c5f4ed6be7487b62dbb1083373c8dbc8"}},"C:\\Users\\keert\\Desktop\\Projects\\EASM\\index.html":{"size":43619,"mtime_ns":1784561227580994600,"word_count":3007,"hashes":{"index.html":"c4c12c039637e5b0d035380772ebbd293db03ccd84eee796e1691cf86435fd84"}},"C:\\Users\\keert\\Desktop\\Projects\\EASM\\public\\app.js":{"size":38310,"mtime_ns":1784561280771868000,"word_count":3088},"C:\\Users\\keert\\Desktop\\Projects\\EASM\\public\\easm_dashboard_studio.json":{"size":10143,"mtime_ns":1784555190870788500,"word_count":607,"hashes":{"public/easm_dashboard_studio.json":"dbca0554bf636d61bc78e8fe70e6339ab06905f38df4906d4402a1feaab9f7b2"}},"C:\\Users\\keert\\Desktop\\Projects\\EASM\\public\\favicon.svg":{"size":479,"mtime_ns":1784546696721842200,"word_count":43,"hashes":{"public/favicon.svg":"7e56c0a81e87e8ea331e974eb710ce0f58cf86793f777acc0aa3cc44044bd6f6"}},"C:\\Users\\keert\\Desktop\\Projects\\EASM\\public\\index.html":{"size":43619,"mtime_ns":1784561246901698500,"word_count":3007,"hashes":{"public/index.html":"80be38b8bc0ac5470af5e19eb4943740134f773e01007cf5c13ae69710b97064"}},"C:\\Users\\keert\\Desktop\\Projects\\EASM\\requirements.txt":{"size":66,"mtime_ns":1784554842517981000,"word_count":8,"hashes":{"requirements.txt":"b944ef84c30fa26919b1274e193f1293da0ec51de55c8f179310e4bedfaa32f4"}},"C:\\Users\\keert\\Desktop\\Projects\\EASM\\scratch\\test_auth_phase1.py":{"size":1964,"mtime_ns":1784555045193850600,"word_count":223,"hashes":{"scratch/test_auth_phase1.py":"771eccb99e8e6b15219d3efadffe7928fb88d8b2396071185009eab524021b28"}},"C:\\Users\\keert\\Desktop\\Projects\\EASM\\scratch\\test_auth_phase2.py":{"size":2872,"mtime_ns":1784561318109992800,"word_count":308,"hashes":{"scratch/test_auth_phase2.py":"af6965cd0eac182f51a730932666b9f601889aa683bbd9bf69a3e5487caaa6d7"}},"C:\\Users\\keert\\Desktop\\Projects\\EASM\\scratch\\test_password_both.py":{"size":857,"mtime_ns":1784555622017137000,"word_count":72,"hashes":{"scratch/test_password_both.py":"d6cdb9bdbfc80b3a74047d6306e84f98641d358d9b7ca0d6d80cec143a297f06"}},"C:\\Users\\keert\\Desktop\\Projects\\EASM\\scratch\\test_rate_limiter.py":{"size":2278,"mtime_ns":1784561113594971800,"word_count":247,"hashes":{"scratch/test_rate_limiter.py":"686adea7434c0ca28473c76d14248ccec5df4f0ceff3ea88bdc613ecd776905f"}},"C:\\Users\\keert\\Desktop\\Projects\\EASM\\simulate_leak.py":{"size":1960,"mtime_ns":1784115292898416400,"word_count":168,"hashes":{"simulate_leak.py":"b9c2f134bc930b37c09e14419264e803f3cfddf12b5cb8e7f7bc612d8f5d45e2"}},"C:\\Users\\keert\\Desktop\\Projects\\EASM\\tests\\event.json":{"size":36,"mtime_ns":1784028892741008000,"word_count":6,"hashes":{"tests/event.json":"1e53acf2ff8005264ec348fa9b40f401ce1fa47e6abeaa2a3b57643dfe90fcac"}},"C:\\Users\\keert\\Desktop\\Projects\\EASM\\vercel.json":{"size":82,"mtime_ns":1784537619922521200,"word_count":11,"hashes":{"vercel.json":"54e0edf27fbd498f2602830638fdb216f2cc16f48ab3fc7a68ea8753405c2539"}},"C:\\Users\\keert\\Desktop\\Projects\\EASM\\web_ui.py":{"size":635,"mtime_ns":1784536416963682400,"word_count":64,"hashes":{"web_ui.py":"f9d26b1e560bf680101e33417b9c27213ad8b9f40343f556a02d5ba2eefd15ed"}}}